PyDistances/__init__.py
PyDistances/binary.py
PyDistances/mixed.py
PyDistances/multiclass.py
PyDistances/quantitative.py
pydistances-0.0.53.dist-info/licenses/LICENSE
pydistances-0.0.53.dist-info/METADATA
pydistances-0.0.53.dist-info/WHEEL
pydistances-0.0.53.dist-info/top_level.txt
pydistances-0.0.53.dist-info/RECORD
