Metadata-Version: 2.4
Name: PyDistances
Version: 0.0.53
Summary: For more information, check out the official documentation of `PyDistances` at: https://fabioscielzoortiz.github.io/PyDistances-book/intro.html
Home-page: https://github.com/FabioScielzoOrtiz/PyDistances-package
Author: Fabio Scielzo Ortiz
Author-email: fabioscielzo98@gmail.com
Classifier: Programming Language :: Python :: 3
Classifier: License :: OSI Approved :: MIT License
Classifier: Operating System :: OS Independent
Requires-Python: >=3.7
License-File: LICENSE
Dynamic: author
Dynamic: author-email
Dynamic: classifier
Dynamic: description
Dynamic: description-content-type
Dynamic: home-page
Dynamic: license-file
Dynamic: requires-python
Dynamic: summary
